arc_utils/__init__.py
arc_utils/aprx.py
arc_utils/gdb.py
arc_utils/mxd.py
arc_utils/output.py
arc_utils/table.py
arc_utils-1.1.dist-info/DESCRIPTION.rst
arc_utils-1.1.dist-info/METADATA
arc_utils-1.1.dist-info/RECORD
arc_utils-1.1.dist-info/WHEEL
arc_utils-1.1.dist-info/metadata.json
arc_utils-1.1.dist-info/top_level.txt
tests/__init__.py
tests/conftest.py
tests/test_aprx.py
tests/test_gdb.py
tests/test_mxd.py
tests/test_table.py
