Metadata-Version: 2.0
Name: arc-utils
Version: 1.1
Summary: Python utilities for use with Esri ArcGIS Desktop, ArcGIS Pro software
Home-page: https://github.com/gdherbert/arc_utils
Author: Grant Herbert
Author-email: gdherbert@gmail.com
License: License:: MIT
Download-URL: https://github.com/gdherbert/arc_utils/tree/1.0
Keywords: esri arcpy arcgis
Platform: UNKNOWN
Classifier: Development Status :: 4 - Beta
Classifier: Intended Audience :: Developers
Classifier: Intended Audience :: End Users/Desktop
Classifier: Programming Language :: Python
Classifier: License :: OSI Approved :: MIT License
Classifier: Environment :: Win32 (MS Windows)
Classifier: Programming Language :: Python :: 2.7
Classifier: Programming Language :: Python :: 3.6
